[
    {
        "name": "Admin",
        "email": "pragyan52yadav@gmail.com",
        "address": "Admin_Address",
        "city": "Admin_City",
        "country": "United States",
        "phone": "9811053230",
        "bloodGroup": "B+",
        "type": "pirogod",
        "adminVerify": true,
        "hash": "$2a$10$H7U6erxuv/BVHUXW6ODkDuk/ruKSvCE9C/yud4DFYE1etLfDudR0K",
        "id": 1,
        "dateCreated": "2022-11-06T19:56:24.852Z",
        "dateUpdated": "2022-11-06T19:56:24.852Z"
    },
    {
        "name": "Org 1",
        "email": "org1@gmail.com",
        "address": "org 1 address",
        "city": "org 1 city",
        "country": "United States",
        "phone": "2347892739",
        "license": "23456",
        "licenseExpiry": "2022-11-17",
        "type": "Hospital",
        "adminVerify": true,
        "hash": "$2a$10$IRVOLhTiRyGwTfbKrGdn5O9lLankHuB3xbj7UET6LiWsbn7em4RJO",
        "id": 2,
        "dateCreated": "2022-11-07T18:20:34.868Z",
        "dateUpdated": "2022-11-07T18:20:34.868Z"
    },
    {
        "name": "dsfgds",
        "email": "sc0rp10n@abc.com",
        "address": "aasdf",
        "city": "asdf",
        "country": "Antigua and Barbuda",
        "phone": "2345653423",
        "license": "dsfgefd",
        "licenseExpiry": "2022-12-21",
        "type": "Hospital",
        "adminVerify": true,
        "hash": "$2a$10$AdF069w0g5kLyK3Zv3uxpeClEFbCiCfUIlKyb4UPFaKm8owSWh.YO",
        "id": 3,
        "dateCreated": "2022-11-28T03:19:06.610Z",
        "dateUpdated": "2022-11-28T03:19:06.610Z"
    },
    {
        "name": "dfv",
        "email": "sc0rsdfasdp10n@abc.com",
        "address": "sdfg",
        "city": "dfg",
        "country": "Angola",
        "phone": "3456435342",
        "speciality": "",
        "organisation": "Org 1",
        "profession": "Nurse",
        "license": "sfgg",
        "licenseExpiry": "2022-12-01",
        "type": "personnel",
        "adminVerify": false,
        "hash": "$2a$10$24I0TtrFYrKn.PVUmFUOtuX.tgSPBDE6NUlh.k0BUb1DRl22qT2X6",
        "id": 4,
        "dateCreated": "2022-11-28T03:35:27.906Z",
        "dateUpdated": "2022-11-28T03:35:27.906Z"
    },
    {
        "name": "asdfasdf",
        "email": "sc0rsdfasdasdfp10n@abc.com",
        "address": "asdfa",
        "city": "asdf",
        "country": "United States",
        "phone": "3245345632",
        "bloodGroup": "B+",
        "type": "patient",
        "adminVerify": false,
        "license": "dsfsghfd",
        "hash": "$2a$10$DVs0UxGq3ZAvyrA5Z4QHNeXm9/h6ejSnB0Xy84WfR5zAjLol.m1hu",
        "id": 5,
        "dateCreated": "2022-11-28T03:38:46.350Z",
        "dateUpdated": "2022-11-28T03:38:46.350Z"
    },
    {
        "name": "Fake User",
        "email": "deeksha20049@iiitd.ac.in",
        "address": "E-34 Budh Vihar Badarpur",
        "city": "Delhi",
        "country": "India",
        "phone": "9717910192",
        "license": "dfsghfds",
        "licenseExpiry": "2022-12-09",
        "type": "Hospital",
        "adminVerify": false,
        "hash": "$2a$10$mkpdFA.5rFj0lT3IfYoap.R1SkfSGZeCG/rtsM7BB0R.2YXpv5tUG",
        "id": 6,
        "dateCreated": "2022-11-28T16:01:21.706Z",
        "dateUpdated": "2022-11-28T16:01:21.706Z"
    }
]